TERRA_GA/IMG_Classification_GA.py
TERRA_GA/__init__.py
TERRA_GA_IMG_Classification-0.0.18.dist-info/LICENSE.txt
TERRA_GA_IMG_Classification-0.0.18.dist-info/METADATA
TERRA_GA_IMG_Classification-0.0.18.dist-info/WHEEL
TERRA_GA_IMG_Classification-0.0.18.dist-info/top_level.txt
TERRA_GA_IMG_Classification-0.0.18.dist-info/RECORD
